sfn_llm_client/__init__.py
sfn_llm_client/agent/agent_executor.py
sfn_llm_client/llm_api_client/__init__.py
sfn_llm_client/llm_api_client/ai21_client.py
sfn_llm_client/llm_api_client/aleph_alpha_client.py
sfn_llm_client/llm_api_client/anthropic_client.py
sfn_llm_client/llm_api_client/base_llm_api_client.py
sfn_llm_client/llm_api_client/cortex_client.py
sfn_llm_client/llm_api_client/cortex_langchain_client.py
sfn_llm_client/llm_api_client/google_client.py
sfn_llm_client/llm_api_client/huggingface_client.py
sfn_llm_client/llm_api_client/llm_api_client_factory.py
sfn_llm_client/llm_api_client/openai_client.py
sfn_llm_client/llm_api_client/openai_langchain_client.py
sfn_llm_client/llm_api_client/snowflake_cortex_complete_extended.py
sfn_llm_client/llm_api_client/core/__init__.py
sfn_llm_client/llm_api_client/core/custom_snowflake.py
sfn_llm_client/llm_api_client/core/llm.py
sfn_llm_client/llm_api_client/core/model_schema.py
sfn_llm_client/llm_client/__init__.py
sfn_llm_client/llm_client/local_client.py
sfn_llm_client/llm_cost_calculation/__init__.py
sfn_llm_client/llm_cost_calculation/anthropic_cost_calculation.py
sfn_llm_client/llm_cost_calculation/cost_tracker.py
sfn_llm_client/llm_cost_calculation/openai_cost_calculation.py
sfn_llm_client/llm_cost_calculation/snowflake_cortex_cost_calculation.py
sfn_llm_client/sync/__init__.py
sfn_llm_client/sync/sync_llm_api_client_factory.py
sfn_llm_client/utils/__init__.py
sfn_llm_client/utils/base_llm_client.py
sfn_llm_client/utils/consts.py
sfn_llm_client/utils/logging.py
sfn_llm_client/utils/retry_with.py
sfn_llm_client-0.3.4.dist-info/METADATA
sfn_llm_client-0.3.4.dist-info/WHEEL
sfn_llm_client-0.3.4.dist-info/top_level.txt
sfn_llm_client-0.3.4.dist-info/RECORD
